pypcfd/__init__.py
pypcfd/fault_diagnosis.py
pypcfd/plotting.py
pypcfd-0.0.2.dist-info/LICENSE
pypcfd-0.0.2.dist-info/METADATA
pypcfd-0.0.2.dist-info/WHEEL
pypcfd-0.0.2.dist-info/top_level.txt
pypcfd-0.0.2.dist-info/RECORD
