Metadata-Version: 2.1
Name: pypcfd
Version: 0.0.2
Summary: Library of tools for fault diagnosis in process control
Home-page: https://github.com/hsaafan/pypcfd
Author: Hussein Saafan
Author-email: hsaafan@uwaterloo.ca
License: UNKNOWN
Platform: UNKNOWN
Classifier: Programming Language :: Python :: 3
Classifier: License :: OSI Approved :: MIT License
Classifier: Operating System :: OS Independent
Requires-Python: >=3.6
License-File: LICENSE
Requires-Dist: numpy
Requires-Dist: scipy
Requires-Dist: matplotlib
